lektor_chameleon.py
lektor_chameleon-0.10.dist-info/licenses/LICENSE.txt
lektor_chameleon-0.10.dist-info/METADATA
lektor_chameleon-0.10.dist-info/WHEEL
lektor_chameleon-0.10.dist-info/entry_points.txt
lektor_chameleon-0.10.dist-info/top_level.txt
lektor_chameleon-0.10.dist-info/RECORD
