Metadata-Version: 2.4
Name: lektor-chameleon
Version: 0.10
Summary: Chameleon template support for Lektor.
Author-email: "H. Turgut Uyar" <uyar@tekir.org>
License-Expression: BSD-3-Clause
Project-URL: repository, https://code.tekir.org/uyar/lektor-chameleon
Keywords: lektor,plugin,chameleon,template
Classifier: Development Status :: 4 - Beta
Classifier: Environment :: Plugins
Classifier: Framework :: Lektor
Classifier: Intended Audience :: Developers
Classifier: Programming Language :: Python
Classifier: Programming Language :: Python :: 3.9
Classifier: Programming Language :: Python :: 3.10
Classifier: Programming Language :: Python :: 3.11
Classifier: Programming Language :: Python :: 3.12
Classifier: Programming Language :: Python :: 3.13
Classifier: Topic :: Internet :: WWW/HTTP :: Site Management
Requires-Python: ~=3.9
License-File: LICENSE.txt
Requires-Dist: chameleon
Dynamic: license-file
